[
  {
    "id": 1,
    "name": "Gipsz Jakab"
  },
  {
    "id": 2,
    "name": "John Doe"
  },
  {
    "id": 3,
    "name": "Kálmán Mikóka"
  },
  {
    "id": 4,
    "name": "Nagymacska"
  },
  {
    "id": 5,
    "name": "Nagymacska"
  },
  {
    "id": 6,
    "name": "balu"
  },
  {
    "id": 7,
    "name": "balu"
  },
  {
    "id": 8,
    "name": "newuser"
  },
  {
    "id": 9,
    "name": "newuser"
  },
  {
    "id": 10,
    "name": "newuser"
  },
  {
    "id": 11,
    "name": "newuser"
  },
  {
    "id": 12,
    "name": "butavagy"
  },
  {
    "id": 13,
    "name": "butavagy"
  },
  {
    "id": 14,
    "name": "butavagy"
  },
  {
    "id": 15,
    "name": "butavagy"
  },
  {
    "id": 16,
    "name": "butavagy"
  },
  {
    "id": 17,
    "name": "butavagy"
  },
  {
    "id": 18,
    "name": "tökfej"
  },
  {
    "id": 19,
    "name": "tökfej"
  },
  {
    "id": 20,
    "name": "tökfej"
  },
  {
    "id": 21,
    "name": "tökfej"
  }
]